LICENSE
MANIFEST.in
Pipfile
Pipfile.lock
README.md
requirements.txt
setup.py
beatsaver_manager.egg-info/PKG-INFO
beatsaver_manager.egg-info/SOURCES.txt
beatsaver_manager.egg-info/dependency_links.txt
beatsaver_manager.egg-info/entry_points.txt
beatsaver_manager.egg-info/requires.txt
beatsaver_manager.egg-info/top_level.txt
bsdl/__init__.py
bsdl/beatsaver.py
bsdl/local.py
bsdl/cli/__init__.py
bsdl/cli/cmd.py
bsdl/cli/main.py
bsdl/cli/utils.py
bsdl/core/__init__.py
bsdl/core/exceptions.py
bsdl/core/models.py
bsdl/core/utils.py