Metadata-Version: 2.1
Name: beatsaver-manager
Version: 0.0.2
Summary: Manager for Custom Beat Saber Playlists and Levels from BeatSaver
Home-page: https://github.com/vlntnwbr/beatsaver-manager
Author: Valentin Weber
Author-email: dev@vweber.eu
License: EUPL
Project-URL: Issue Tracker, https://github.com/vlntnwbr/beatsaver-manager/issues
Project-URL: Bug Tracker, https://github.com/vlntnwbr/beatsaver-manager/labels/bug
Platform: UNKNOWN
Classifier: Development Status :: 3 - Alpha
Classifier: Environment :: Console
Classifier: Intended Audience :: End Users/Desktop
Classifier: License :: OSI Approved :: European Union Public Licence 1.2 (EUPL 1.2)
Classifier: Natural Language :: English
Classifier: Operating System :: Microsoft :: Windows
Classifier: Programming Language :: Python :: 3
Classifier: Programming Language :: Python :: 3.10
Classifier: Topic :: Desktop Environment :: File Managers
Classifier: Topic :: Games/Entertainment
Classifier: Topic :: Utilities
License-File: LICENSE
